fluteline.py
fluteline/__init__.py
fluteline/nodes.py
fluteline/queue.py
fluteline/queues.py
fluteline/utils.py
fluteline-0.0.8.dist-info/METADATA
fluteline-0.0.8.dist-info/RECORD
fluteline-0.0.8.dist-info/WHEEL
fluteline-0.0.8.dist-info/top_level.txt
