Metadata-Version: 2.1
Name: fluteline
Version: 0.0.8
Summary: Easy thread based pipelines
Home-page: https://github.com/Nagasaki45/fluteline
Author: Tom Gurion
Author-email: nagasaki45@gmail.com
License: UNKNOWN
Keywords: pipeline flow thread
Platform: UNKNOWN
Classifier: Development Status :: 3 - Alpha
Classifier: Intended Audience :: Developers
Classifier: Topic :: Software Development :: Build Tools
Classifier: License :: OSI Approved :: MIT License
Classifier: Programming Language :: Python :: 2
Classifier: Programming Language :: Python :: 2.7
Classifier: Programming Language :: Python :: 3
Classifier: Programming Language :: Python :: 3.4
Classifier: Programming Language :: Python :: 3.5
Classifier: Programming Language :: Python :: 3.6
Classifier: Topic :: Utilities
